Print_Hello/__init__.py
Print_Hello/main.py
Huangyichang-0.1.dist-info/METADATA
Huangyichang-0.1.dist-info/WHEEL
Huangyichang-0.1.dist-info/top_level.txt
Huangyichang-0.1.dist-info/RECORD
